{
  "generated_at": "2026-07-22T19:03:40+07:00",
  "repo": "MonitoringUangRakyat/monitoring-rakyat",
  "input_present": false,
  "public_submissions_captured": 0,
  "queue_json": "gudang-db/_queue/public_submissions.json",
  "queue_csv": "gudang-db/_queue/public_submissions.csv",
  "note": "No new anonymous public-intake dispatch submissions; retained existing anonymized queue.",
  "promoted_at": "2026-07-22T19:03:40+07:00",
  "public_submissions_ready_for_audit": 0,
  "public_submissions_promoted_to_intake": 0,
  "public_korupsi_rows_mapped": 0,
  "public_korupsi_rows_promoted": 0,
  "promotion_rule": ">=50 validity score masuk intake publik dan mapping CSV Gudang DB draft; final tetap wajib audit sumber."
}
